coderefineai_executor/__init__.py
coderefineai_executor/config.py
coderefineai_executor/executor.py
coderefineai_executor/main.py
coderefineai_executor/utils.py
coderefineai_executor-0.1.5.dist-info/METADATA
coderefineai_executor-0.1.5.dist-info/WHEEL
coderefineai_executor-0.1.5.dist-info/top_level.txt
coderefineai_executor-0.1.5.dist-info/RECORD
