Metadata-Version: 2.2
Name: coderefineai_executor
Version: 0.1.5
Home-page: https://github.com/harish876/CodeRefineAI/coderefineai_executor
Author: harish876
Author-email: harishgokul01@gmail.com
Classifier: Programming Language :: Python :: 3
Classifier: License :: OSI Approved :: MIT License
Classifier: Operating System :: OS Independent
Requires-Python: >=3.6
Requires-Dist: pandas
Requires-Dist: requests
Requires-Dist: pydantic
Requires-Dist: pydantic-settings
Dynamic: author
Dynamic: author-email
Dynamic: classifier
Dynamic: description
Dynamic: description-content-type
Dynamic: home-page
Dynamic: requires-dist
Dynamic: requires-python
